{"nodes": [{"id": "wsl_localhost_ubuntu_home_bossman_projects_vibescent_src_vibescents_cli_py", "label": "cli.py", "file_type": "code", "source_file": "\\\\wsl.localhost\\Ubuntu\\home\\bossman\\projects\\vibescent\\src\\vibescents\\cli.py", "source_location": "L1"}, {"id": "cli_build_parser", "label": "build_parser()", "file_type": "code", "source_file": "\\\\wsl.localhost\\Ubuntu\\home\\bossman\\projects\\vibescent\\src\\vibescents\\cli.py", "source_location": "L17"}, {"id": "cli_main", "label": "main()", "file_type": "code", "source_file": "\\\\wsl.localhost\\Ubuntu\\home\\bossman\\projects\\vibescent\\src\\vibescents\\cli.py", "source_location": "L65"}], "edges": [{"source": "wsl_localhost_ubuntu_home_bossman_projects_vibescent_src_vibescents_cli_py", "target": "argparse", "relation": "imports", "confidence": "EXTRACTED", "source_file": "\\\\wsl.localhost\\Ubuntu\\home\\bossman\\projects\\vibescent\\src\\vibescents\\cli.py", "source_location": "L3", "weight": 1.0}, {"source": "wsl_localhost_ubuntu_home_bossman_projects_vibescent_src_vibescents_cli_py", "target": "pathlib", "relation": "imports_from", "confidence": "EXTRACTED", "source_file": "\\\\wsl.localhost\\Ubuntu\\home\\bossman\\projects\\vibescent\\src\\vibescents\\cli.py", "source_location": "L4", "weight": 1.0}, {"source": "wsl_localhost_ubuntu_home_bossman_projects_vibescent_src_vibescents_cli_py", "target": "vibescents_benchmark", "relation": "imports_from", "confidence": "EXTRACTED", "source_file": "\\\\wsl.localhost\\Ubuntu\\home\\bossman\\projects\\vibescent\\src\\vibescents\\cli.py", "source_location": "L6", "weight": 1.0}, {"source": "wsl_localhost_ubuntu_home_bossman_projects_vibescent_src_vibescents_cli_py", "target": "vibescents_io_utils", "relation": "imports_from", "confidence": "EXTRACTED", "source_file": "\\\\wsl.localhost\\Ubuntu\\home\\bossman\\projects\\vibescent\\src\\vibescents\\cli.py", "source_location": "L7", "weight": 1.0}, {"source": "wsl_localhost_ubuntu_home_bossman_projects_vibescent_src_vibescents_cli_py", "target": "vibescents_pipelines", "relation": "imports_from", "confidence": "EXTRACTED", "source_file": "\\\\wsl.localhost\\Ubuntu\\home\\bossman\\projects\\vibescent\\src\\vibescents\\cli.py", "source_location": "L8", "weight": 1.0}, {"source": "wsl_localhost_ubuntu_home_bossman_projects_vibescent_src_vibescents_cli_py", "target": "vibescents_reranker", "relation": "imports_from", "confidence": "EXTRACTED", "source_file": "\\\\wsl.localhost\\Ubuntu\\home\\bossman\\projects\\vibescent\\src\\vibescents\\cli.py", "source_location": "L13", "weight": 1.0}, {"source": "wsl_localhost_ubuntu_home_bossman_projects_vibescent_src_vibescents_cli_py", "target": "vibescents_schemas", "relation": "imports_from", "confidence": "EXTRACTED", "source_file": "\\\\wsl.localhost\\Ubuntu\\home\\bossman\\projects\\vibescent\\src\\vibescents\\cli.py", "source_location": "L14", "weight": 1.0}, {"source": "wsl_localhost_ubuntu_home_bossman_projects_vibescent_src_vibescents_cli_py", "target": "cli_build_parser", "relation": "contains", "confidence": "EXTRACTED", "source_file": "\\\\wsl.localhost\\Ubuntu\\home\\bossman\\projects\\vibescent\\src\\vibescents\\cli.py", "source_location": "L17", "weight": 1.0}, {"source": "wsl_localhost_ubuntu_home_bossman_projects_vibescent_src_vibescents_cli_py", "target": "cli_main", "relation": "contains", "confidence": "EXTRACTED", "source_file": "\\\\wsl.localhost\\Ubuntu\\home\\bossman\\projects\\vibescent\\src\\vibescents\\cli.py", "source_location": "L65", "weight": 1.0}, {"source": "cli_main", "target": "cli_build_parser", "relation": "calls", "confidence": "EXTRACTED", "source_file": "\\\\wsl.localhost\\Ubuntu\\home\\bossman\\projects\\vibescent\\src\\vibescents\\cli.py", "source_location": "L66", "weight": 1.0}], "raw_calls": [{"caller_nid": "cli_build_parser", "callee": "ArgumentParser", "source_file": "\\\\wsl.localhost\\Ubuntu\\home\\bossman\\projects\\vibescent\\src\\vibescents\\cli.py", "source_location": "L18"}, {"caller_nid": "cli_build_parser", "callee": "add_subparsers", "source_file": "\\\\wsl.localhost\\Ubuntu\\home\\bossman\\projects\\vibescent\\src\\vibescents\\cli.py", "source_location": "L19"}, {"caller_nid": "cli_build_parser", "callee": "add_parser", "source_file": "\\\\wsl.localhost\\Ubuntu\\home\\bossman\\projects\\vibescent\\src\\vibescents\\cli.py", "source_location": "L21"}, {"caller_nid": "cli_build_parser", "callee": "add_argument", "source_file": "\\\\wsl.localhost\\Ubuntu\\home\\bossman\\projects\\vibescent\\src\\vibescents\\cli.py", "source_location": "L22"}, {"caller_nid": "cli_build_parser", "callee": "add_argument", "source_file": "\\\\wsl.localhost\\Ubuntu\\home\\bossman\\projects\\vibescent\\src\\vibescents\\cli.py", "source_location": "L23"}, {"caller_nid": "cli_build_parser", "callee": "add_argument", "source_file": "\\\\wsl.localhost\\Ubuntu\\home\\bossman\\projects\\vibescent\\src\\vibescents\\cli.py", "source_location": "L24"}, {"caller_nid": "cli_build_parser", "callee": "add_argument", "source_file": "\\\\wsl.localhost\\Ubuntu\\home\\bossman\\projects\\vibescent\\src\\vibescents\\cli.py", "source_location": "L25"}, {"caller_nid": "cli_build_parser", "callee": "add_argument", "source_file": "\\\\wsl.localhost\\Ubuntu\\home\\bossman\\projects\\vibescent\\src\\vibescents\\cli.py", "source_location": "L26"}, {"caller_nid": "cli_build_parser", "callee": "add_argument", "source_file": "\\\\wsl.localhost\\Ubuntu\\home\\bossman\\projects\\vibescent\\src\\vibescents\\cli.py", "source_location": "L27"}, {"caller_nid": "cli_build_parser", "callee": "add_parser", "source_file": "\\\\wsl.localhost\\Ubuntu\\home\\bossman\\projects\\vibescent\\src\\vibescents\\cli.py", "source_location": "L33"}, {"caller_nid": "cli_build_parser", "callee": "add_argument", "source_file": "\\\\wsl.localhost\\Ubuntu\\home\\bossman\\projects\\vibescent\\src\\vibescents\\cli.py", "source_location": "L34"}, {"caller_nid": "cli_build_parser", "callee": "add_argument", "source_file": "\\\\wsl.localhost\\Ubuntu\\home\\bossman\\projects\\vibescent\\src\\vibescents\\cli.py", "source_location": "L35"}, {"caller_nid": "cli_build_parser", "callee": "add_parser", "source_file": "\\\\wsl.localhost\\Ubuntu\\home\\bossman\\projects\\vibescent\\src\\vibescents\\cli.py", "source_location": "L37"}, {"caller_nid": "cli_build_parser", "callee": "add_argument", "source_file": "\\\\wsl.localhost\\Ubuntu\\home\\bossman\\projects\\vibescent\\src\\vibescents\\cli.py", "source_location": "L38"}, {"caller_nid": "cli_build_parser", "callee": "add_argument", "source_file": "\\\\wsl.localhost\\Ubuntu\\home\\bossman\\projects\\vibescent\\src\\vibescents\\cli.py", "source_location": "L39"}, {"caller_nid": "cli_build_parser", "callee": "add_argument", "source_file": "\\\\wsl.localhost\\Ubuntu\\home\\bossman\\projects\\vibescent\\src\\vibescents\\cli.py", "source_location": "L40"}, {"caller_nid": "cli_build_parser", "callee": "add_argument", "source_file": "\\\\wsl.localhost\\Ubuntu\\home\\bossman\\projects\\vibescent\\src\\vibescents\\cli.py", "source_location": "L41"}, {"caller_nid": "cli_build_parser", "callee": "add_argument", "source_file": "\\\\wsl.localhost\\Ubuntu\\home\\bossman\\projects\\vibescent\\src\\vibescents\\cli.py", "source_location": "L42"}, {"caller_nid": "cli_build_parser", "callee": "add_argument", "source_file": "\\\\wsl.localhost\\Ubuntu\\home\\bossman\\projects\\vibescent\\src\\vibescents\\cli.py", "source_location": "L43"}, {"caller_nid": "cli_build_parser", "callee": "add_argument", "source_file": "\\\\wsl.localhost\\Ubuntu\\home\\bossman\\projects\\vibescent\\src\\vibescents\\cli.py", "source_location": "L44"}, {"caller_nid": "cli_build_parser", "callee": "add_parser", "source_file": "\\\\wsl.localhost\\Ubuntu\\home\\bossman\\projects\\vibescent\\src\\vibescents\\cli.py", "source_location": "L46"}, {"caller_nid": "cli_build_parser", "callee": "add_argument", "source_file": "\\\\wsl.localhost\\Ubuntu\\home\\bossman\\projects\\vibescent\\src\\vibescents\\cli.py", "source_location": "L47"}, {"caller_nid": "cli_build_parser", "callee": "add_argument", "source_file": "\\\\wsl.localhost\\Ubuntu\\home\\bossman\\projects\\vibescent\\src\\vibescents\\cli.py", "source_location": "L48"}, {"caller_nid": "cli_build_parser", "callee": "add_argument", "source_file": "\\\\wsl.localhost\\Ubuntu\\home\\bossman\\projects\\vibescent\\src\\vibescents\\cli.py", "source_location": "L49"}, {"caller_nid": "cli_build_parser", "callee": "add_argument", "source_file": "\\\\wsl.localhost\\Ubuntu\\home\\bossman\\projects\\vibescent\\src\\vibescents\\cli.py", "source_location": "L50"}, {"caller_nid": "cli_build_parser", "callee": "add_parser", "source_file": "\\\\wsl.localhost\\Ubuntu\\home\\bossman\\projects\\vibescent\\src\\vibescents\\cli.py", "source_location": "L52"}, {"caller_nid": "cli_build_parser", "callee": "add_argument", "source_file": "\\\\wsl.localhost\\Ubuntu\\home\\bossman\\projects\\vibescent\\src\\vibescents\\cli.py", "source_location": "L53"}, {"caller_nid": "cli_build_parser", "callee": "add_argument", "source_file": "\\\\wsl.localhost\\Ubuntu\\home\\bossman\\projects\\vibescent\\src\\vibescents\\cli.py", "source_location": "L54"}, {"caller_nid": "cli_build_parser", "callee": "add_argument", "source_file": "\\\\wsl.localhost\\Ubuntu\\home\\bossman\\projects\\vibescent\\src\\vibescents\\cli.py", "source_location": "L55"}, {"caller_nid": "cli_build_parser", "callee": "add_argument", "source_file": "\\\\wsl.localhost\\Ubuntu\\home\\bossman\\projects\\vibescent\\src\\vibescents\\cli.py", "source_location": "L56"}, {"caller_nid": "cli_main", "callee": "parse_args", "source_file": "\\\\wsl.localhost\\Ubuntu\\home\\bossman\\projects\\vibescent\\src\\vibescents\\cli.py", "source_location": "L66"}, {"caller_nid": "cli_main", "callee": "load_dataframe", "source_file": "\\\\wsl.localhost\\Ubuntu\\home\\bossman\\projects\\vibescent\\src\\vibescents\\cli.py", "source_location": "L69"}, {"caller_nid": "cli_main", "callee": "embed_text_frame", "source_file": "\\\\wsl.localhost\\Ubuntu\\home\\bossman\\projects\\vibescent\\src\\vibescents\\cli.py", "source_location": "L70"}, {"caller_nid": "cli_main", "callee": "load_json", "source_file": "\\\\wsl.localhost\\Ubuntu\\home\\bossman\\projects\\vibescent\\src\\vibescents\\cli.py", "source_location": "L81"}, {"caller_nid": "cli_main", "callee": "embed_occasions", "source_file": "\\\\wsl.localhost\\Ubuntu\\home\\bossman\\projects\\vibescent\\src\\vibescents\\cli.py", "source_location": "L82"}, {"caller_nid": "cli_main", "callee": "load_dataframe", "source_file": "\\\\wsl.localhost\\Ubuntu\\home\\bossman\\projects\\vibescent\\src\\vibescents\\cli.py", "source_location": "L86"}, {"caller_nid": "cli_main", "callee": "retrieve_with_multimodal_query", "source_file": "\\\\wsl.localhost\\Ubuntu\\home\\bossman\\projects\\vibescent\\src\\vibescents\\cli.py", "source_location": "L87"}, {"caller_nid": "cli_main", "callee": "load_json", "source_file": "\\\\wsl.localhost\\Ubuntu\\home\\bossman\\projects\\vibescent\\src\\vibescents\\cli.py", "source_location": "L99"}, {"caller_nid": "cli_main", "callee": "model_validate", "source_file": "\\\\wsl.localhost\\Ubuntu\\home\\bossman\\projects\\vibescent\\src\\vibescents\\cli.py", "source_location": "L101"}, {"caller_nid": "cli_main", "callee": "rerank", "source_file": "\\\\wsl.localhost\\Ubuntu\\home\\bossman\\projects\\vibescent\\src\\vibescents\\cli.py", "source_location": "L103"}, {"caller_nid": "cli_main", "callee": "GeminiReranker", "source_file": "\\\\wsl.localhost\\Ubuntu\\home\\bossman\\projects\\vibescent\\src\\vibescents\\cli.py", "source_location": "L103"}, {"caller_nid": "cli_main", "callee": "Path", "source_file": "\\\\wsl.localhost\\Ubuntu\\home\\bossman\\projects\\vibescent\\src\\vibescents\\cli.py", "source_location": "L108"}, {"caller_nid": "cli_main", "callee": "ensure_dir", "source_file": "\\\\wsl.localhost\\Ubuntu\\home\\bossman\\projects\\vibescent\\src\\vibescents\\cli.py", "source_location": "L109"}, {"caller_nid": "cli_main", "callee": "dump_json", "source_file": "\\\\wsl.localhost\\Ubuntu\\home\\bossman\\projects\\vibescent\\src\\vibescents\\cli.py", "source_location": "L110"}, {"caller_nid": "cli_main", "callee": "model_dump", "source_file": "\\\\wsl.localhost\\Ubuntu\\home\\bossman\\projects\\vibescent\\src\\vibescents\\cli.py", "source_location": "L110"}, {"caller_nid": "cli_main", "callee": "load_json", "source_file": "\\\\wsl.localhost\\Ubuntu\\home\\bossman\\projects\\vibescent\\src\\vibescents\\cli.py", "source_location": "L114"}, {"caller_nid": "cli_main", "callee": "Settings", "source_file": "\\\\wsl.localhost\\Ubuntu\\home\\bossman\\projects\\vibescent\\src\\vibescents\\cli.py", "source_location": "L119"}, {"caller_nid": "cli_main", "callee": "from_env", "source_file": "\\\\wsl.localhost\\Ubuntu\\home\\bossman\\projects\\vibescent\\src\\vibescents\\cli.py", "source_location": "L120"}, {"caller_nid": "cli_main", "callee": "BenchmarkGenerator", "source_file": "\\\\wsl.localhost\\Ubuntu\\home\\bossman\\projects\\vibescent\\src\\vibescents\\cli.py", "source_location": "L122"}, {"caller_nid": "cli_main", "callee": "generate_case_labels", "source_file": "\\\\wsl.localhost\\Ubuntu\\home\\bossman\\projects\\vibescent\\src\\vibescents\\cli.py", "source_location": "L125"}, {"caller_nid": "cli_main", "callee": "append", "source_file": "\\\\wsl.localhost\\Ubuntu\\home\\bossman\\projects\\vibescent\\src\\vibescents\\cli.py", "source_location": "L130"}, {"caller_nid": "cli_main", "callee": "model_dump", "source_file": "\\\\wsl.localhost\\Ubuntu\\home\\bossman\\projects\\vibescent\\src\\vibescents\\cli.py", "source_location": "L130"}, {"caller_nid": "cli_main", "callee": "consolidate_case_drafts", "source_file": "\\\\wsl.localhost\\Ubuntu\\home\\bossman\\projects\\vibescent\\src\\vibescents\\cli.py", "source_location": "L130"}, {"caller_nid": "cli_main", "callee": "Path", "source_file": "\\\\wsl.localhost\\Ubuntu\\home\\bossman\\projects\\vibescent\\src\\vibescents\\cli.py", "source_location": "L131"}, {"caller_nid": "cli_main", "callee": "ensure_dir", "source_file": "\\\\wsl.localhost\\Ubuntu\\home\\bossman\\projects\\vibescent\\src\\vibescents\\cli.py", "source_location": "L132"}, {"caller_nid": "cli_main", "callee": "dump_json", "source_file": "\\\\wsl.localhost\\Ubuntu\\home\\bossman\\projects\\vibescent\\src\\vibescents\\cli.py", "source_location": "L133"}, {"caller_nid": "cli_main", "callee": "ValueError", "source_file": "\\\\wsl.localhost\\Ubuntu\\home\\bossman\\projects\\vibescent\\src\\vibescents\\cli.py", "source_location": "L136"}]}